cnsbm/__init__.py
cnsbm/cnsbm.py
cnsbm/cnsbm_trainer.py
cnsbm/utils_cnsbm.py
cnsbm/utils_trainer.py
cnsbm-1.0.1.dist-info/licenses/LICENSE
cnsbm-1.0.1.dist-info/METADATA
cnsbm-1.0.1.dist-info/WHEEL
cnsbm-1.0.1.dist-info/top_level.txt
cnsbm-1.0.1.dist-info/RECORD
