Metadata-Version: 2.4
Name: cnsbm
Version: 1.0.1
Summary: Categorical Block Modelling For Primary and Residual Copy Number Variation
Author-email: Kevin Lam <kevin.lam@stat.ubc.ca>
License-Expression: MIT
Project-URL: Homepage, https://github.com/lamke07/CNSBM
Project-URL: Documentation, https://github.com/lamke07/CNSBM#readme
Project-URL: Repository, https://github.com/lamke07/CNSBM
Project-URL: Bug Tracker, https://github.com/lamke07/CNSBM/issues
Project-URL: Paper, https://arxiv.org/abs/2506.22963
Keywords: machine learning,stochastic block model,copy number variation,bioinformatics,clustering,variational inference
Classifier: Development Status :: 4 - Beta
Classifier: Intended Audience :: Science/Research
Classifier: Operating System :: OS Independent
Classifier: Programming Language :: Python :: 3
Classifier: Programming Language :: Python :: 3.9
Classifier: Programming Language :: Python :: 3.10
Classifier: Programming Language :: Python :: 3.11
Classifier: Topic :: Scientific/Engineering :: Artificial Intelligence
Classifier: Topic :: Scientific/Engineering :: Bio-Informatics
Requires-Python: >=3.9
License-File: LICENSE
Requires-Dist: numpy>=1.21.0
Requires-Dist: pandas>=1.3.0
Requires-Dist: scipy>=1.7.0
Requires-Dist: scikit-learn>=1.0.0
Requires-Dist: matplotlib>=3.3.0
Requires-Dist: seaborn>=0.11.0
Requires-Dist: jax>=0.3.0
Provides-Extra: dev
Requires-Dist: pytest>=6.0; extra == "dev"
Requires-Dist: pytest-cov; extra == "dev"
Requires-Dist: black; extra == "dev"
Requires-Dist: flake8; extra == "dev"
Requires-Dist: mypy; extra == "dev"
Requires-Dist: jupyter; extra == "dev"
Dynamic: license-file
